{
  "user-data": {
    "id": 1,
    "user_name": "Jorge Solano",
    "user_desc": "Beneficiario",
    "user_img": "https://via.placeholder.com/100"
  },
  "nav-links": [
    {
      "id": 1,
      "item_name": "Pedir Aguila",
      "fa_icon": "fa-car-side"
    },
    {
      "id": 2,
      "item_name": "Vuelos",
      "fa_icon": "fa-map-marker-alt"
    },
    {
      "id": 3,
      "item_name": "Rutas",
      "fa_icon": "fa-route"
    },
    {
      "id": 4,
      "item_name": "Administrar",
      "fa_icon": "fa-tachometer-alt"
    },
    {
      "id": 5,
      "item_name": "Estadisticas",
      "fa_icon": "fa-chart-bar"
    },
    {
      "id": 6,
      "item_name": "Metodos de pago",
      "fa_icon": "fa-wallet"
    },
    {
      "id": 7,
      "item_name": "Cerrar Sesión",
      "fa_icon": "fa-sign-out-alt"
    }
  ],
  "ride-profile": [
    {
      "id": 1,
      "profile_name": "Para mi",
      "profile_img": "https://via.placeholder.com/100"
    },
    {
      "id": 2,
      "profile_name": "Colega",
      "profile_img": "https://via.placeholder.com/100"
    },
    {
      "id": 3,
      "profile_name": "Invitado",
      "profile_img": "https://via.placeholder.com/100"
    }
  ],
  "steps-data": [
    {
      "id": 1,
      "step_number": 1,
      "step_label": "Origen",
      "step_route": "/ride/origin"
    },
    {
      "id": 2,
      "step_number": 2,
      "step_label": "Destino",
      "step_route": "/ride/destination"
    },
    {
      "id": 3,
      "step_number": 3,
      "step_label": "",
      "step_route": ""
    },
    {
      "id": 4,
      "step_number": 4,
      "step_label": "",
      "step_route": ""
    },
    {
      "id": 5,
      "step_number": 5,
      "step_label": "",
      "step_route": ""
    },
    {
      "id": 6,
      "step_number": 6,
      "step_label": "",
      "step_route": ""
    }
  ],
  "favorite-list": [
    {
      "id": 1,
      "favorite_name": "Ivesur",
      "favorite_address": "Cra. 56 #19-84, Bogotá, Colombia",
      "lat": 4.6,
      "lng": -74.13
    },
    {
      "id": 2,
      "favorite_name": "Mi Águila",
      "favorite_address": "Carrera 15 80-90, Bogotá, Colombia",
      "lat": 4.61,
      "lng": -74.13
    },
    {
      "id": 3,
      "favorite_name": "Aeropuerto El Dorado",
      "favorite_address": "Bogotá, Colombia",
      "lat": 4.62,
      "lng": -74.13
    },
    {
      "id": 4,
      "favorite_name": "Work",
      "favorite_address": "Bogotá, Colombia",
      "lat": 4.63,
      "lng": -74.13
    },
    {
      "id": 5,
      "favorite_name": "Home",
      "favorite_address": "Bogotá, Colombia",
      "lat": 4.64,
      "lng": -74.13
    },
    {
      "id": 6,
      "favorite_name": "Sweetheart",
      "favorite_address": "Bogotá, Colombia",
      "lat": 4.65,
      "lng": -74.13
    },
    {
      "id": 7,
      "favorite_name": "Dads work",
      "favorite_address": "Bogotá, Colombia",
      "lat": 4.67,
      "lng": -74.13
    }
  ],
  "default-route": {
    "origin": {
      "lat": 4.72,
      "lng": -74.13
    },
    "destination": {
      "lat": 4.6672736,
      "lng": -74.0586661
    }
  }
}
